colanderpy/__init__.py
colanderpy/pi_function.py
colanderpy/sieve.py
colanderpy-0.7.2.dist-info/METADATA
colanderpy-0.7.2.dist-info/WHEEL
colanderpy-0.7.2.dist-info/entry_points.txt
colanderpy-0.7.2.dist-info/top_level.txt
colanderpy-0.7.2.dist-info/RECORD
