Metadata-Version: 2.4
Name: colanderpy
Version: 0.7.2
Summary: A simple version of the Sieve of Eratosthenes. Developed during "Python for Scientific Computing" course at CINECA
Author-email: Sergio Orlandini <s.orlandini@cineca.it>, Michele Mastropietro <m.mastropietro@cineca.it>
License-Expression: GPL-3.0-or-later
Project-URL: Homepage, https://gitlab.hpc.cineca.it/cineca-hpyc/colanderpy
Classifier: Programming Language :: Python :: 3
Classifier: Development Status :: 3 - Alpha
Classifier: Operating System :: OS Independent
Classifier: Topic :: Education
Requires-Python: >=3.9
Requires-Dist: numpy>=1.21
Provides-Extra: dev
Requires-Dist: pytest>=7.0; extra == "dev"
Requires-Dist: pytest-cov>=4.0; extra == "dev"
